flopsy/__init__.py
flopsy/action.py
flopsy/reducer.py
flopsy/saga.py
flopsy/store.py
flopsy/inspector/inspector.py
flopsy-0.0.4.dist-info/LICENSE.txt
flopsy-0.0.4.dist-info/METADATA
flopsy-0.0.4.dist-info/WHEEL
flopsy-0.0.4.dist-info/top_level.txt
flopsy-0.0.4.dist-info/RECORD
